frametests/DBTests.py
frametests/Test.py
frametests/__init__.py
frametests/style.py
frametests/tests.py
frametests/utils.py
frametests-0.1.1.dist-info/METADATA
frametests-0.1.1.dist-info/WHEEL
frametests-0.1.1.dist-info/top_level.txt
frametests-0.1.1.dist-info/RECORD
