Metadata-Version: 2.1
Name: frametests
Version: 0.1.1
Summary: A library for testing and analyzing data integrity.
Home-page: UNKNOWN
Author: Atai Ambus
Author-email: UNKNOWN
License: MIT
Platform: UNKNOWN
